open_in_mpv/__init__.py
open_in_mpv/__main__.py
open_in_mpv/constants.py
open_in_mpv/install.py
open_in_mpv/main.py
open_in_mpv/py.typed
open_in_mpv/test_open.py
open_in_mpv/uninstall.py
open_in_mpv/utils.py
open_in_mpv-0.1.3.dist-info/LICENSE.txt
open_in_mpv-0.1.3.dist-info/METADATA
open_in_mpv-0.1.3.dist-info/WHEEL
open_in_mpv-0.1.3.dist-info/entry_points.txt
open_in_mpv-0.1.3.dist-info/RECORD
