Metadata-Version: 2.3
Name: open-in-mpv
Version: 0.1.3
Summary: Host-side of the extension to open any link or page URL in mpv via the browser context menu.
License: MIT
Keywords: audio,browser extension,multimedia,mpv,video
Author: Andrew Udvare
Author-email: audvare@gmail.com
Requires-Python: >=3.10,<3.14
Classifier: Development Status :: 2 - Pre-Alpha
Classifier: Intended Audience :: Developers
Classifier: License :: OSI Approved :: MIT License
Classifier: Programming Language :: Python
Classifier: Programming Language :: Python :: 3.10
Classifier: Programming Language :: Python :: 3.11
Classifier: Programming Language :: Python :: 3.12
Classifier: Programming Language :: Python :: 3.13
Classifier: Typing :: Typed
Requires-Dist: click (>=8.1.8,<9.0.0)
Requires-Dist: colorlog (>=6.9.0,<7.0.0)
Requires-Dist: platformdirs (>=4.3.6,<5.0.0)
Requires-Dist: typing-extensions (>=4.13.1,<5.0.0)
Project-URL: Documentation, https://open-in-mpv.readthedocs.org
Project-URL: Homepage, https://tatsh.github.io/open-in-mpv/
Project-URL: Issues, https://github.com/Tatsh/open-in-mpv/issues
Project-URL: Repository, https://github.com/Tatsh/open-in-mpv
